LICENSE
README.md
setup.py
flask_apscheduler_plus/__init__.py
flask_apscheduler_plus/api.py
flask_apscheduler_plus/auth.py
flask_apscheduler_plus/json.py
flask_apscheduler_plus/scheduler.py
flask_apscheduler_plus/utils.py
flask_apscheduler_plus.egg-info/PKG-INFO
flask_apscheduler_plus.egg-info/SOURCES.txt
flask_apscheduler_plus.egg-info/dependency_links.txt
flask_apscheduler_plus.egg-info/requires.txt
flask_apscheduler_plus.egg-info/top_level.txt
flask_apscheduler_plus/jobstores/__init__.py
flask_apscheduler_plus/jobstores/redis.py